sqlconvert/__init__.py
sqlconvert/__version__.py
sqlconvert/print_tokens.py
sqlconvert/process_mysql.py
sqlconvert/process_tokens.py
sqlconvert-0.3.0.data/scripts/mysql2sql
sqlconvert-0.3.0.dist-info/METADATA
sqlconvert-0.3.0.dist-info/RECORD
sqlconvert-0.3.0.dist-info/WHEEL
sqlconvert-0.3.0.dist-info/top_level.txt
