Metadata-Version: 2.1
Name: sqlconvert
Version: 0.3.0
Summary: Broytman sqlconvert
Home-page: https://phdru.name/Software/Python/sqlconvert/
Author: Oleg Broytman
Author-email: phd@phdru.name
License: GPL
Project-URL: Homepage, https://phdru.name/Software/Python/sqlconvert/
Project-URL: Documentation, https://phdru.name/Software/Python/sqlconvert/docs/
Project-URL: Github repo, https://github.com/phdru/sqlconvert
Project-URL: Issue tracker, https://github.com/phdru/sqlconvert/issues
Project-URL: Download, https://pypi.org/project/sqlconvert/0.3.0/
Project-URL: Git repo, https://git.phdru.name/sqlconvert.git/
Keywords: sql,mysql,postgresql,sqlite,insert
Platform: Any
Classifier: Development Status :: 3 - Alpha
Classifier: Environment :: Console
Classifier: Intended Audience :: Developers
Classifier: License :: OSI Approved :: GNU General Public License (GPL)
Classifier: Operating System :: OS Independent
Classifier: Programming Language :: Python :: 2
Classifier: Programming Language :: Python :: 2.7
Classifier: Programming Language :: Python :: 3
Classifier: Programming Language :: Python :: 3.4
Classifier: Programming Language :: Python :: 3.5
Classifier: Programming Language :: Python :: 3.6
Classifier: Programming Language :: Python :: 3.7
Classifier: Programming Language :: Python :: 3.8
Requires-Python: >=2.7, !=3.0.*, !=3.1.*, !=3.2.*, !=3.3.*
